flync/__init__.py
flync/api.py
flync/cli.py
flync/assets/__init__.py
flync/assets/flync_ebm_model.pkl
flync/assets/flync_ebm_model_HOLDOUT.pkl
flync/assets/flync_ebm_model_params.json
flync/assets/flync_ebm_model_schema.json
flync/assets/flync_ebm_scaler.pkl
flync/features/__init__.py
flync/features/bwq.py
flync/features/feature_cleaning.py
flync/features/feature_wrapper.py
flync/features/kmer.py
flync/features/mfe.py
flync/ml/__init__.py
flync/ml/ebm_predictor.py
flync/ml/example_usage.py
flync/ml/extract_model_schema.py
flync/ml/predict_test.py
flync/ml/predictor.py
flync/ml/schema_extractor.py
flync/ml/schema_validator.py
flync/optimizer/__init__.py
flync/optimizer/batch_optimization.py
flync/optimizer/hyperparameter_optimizer.py
flync/utils/__init__.py
flync/utils/kmer_redux.py
flync/utils/progress.py
flync/utils/util_sparse_to_parquet.py
flync/workflows/Snakefile
flync/workflows/rules/assembly.smk
flync/workflows/rules/dge.smk
flync/workflows/rules/mapping.smk
flync/workflows/rules/merge.smk
flync/workflows/rules/quantify.smk
flync/workflows/scripts/ballgown_dge.R
flync/workflows/scripts/predownload_tracks.py
flync-1.0.2.dist-info/licenses/LICENSE
flync-1.0.2.dist-info/METADATA
flync-1.0.2.dist-info/WHEEL
flync-1.0.2.dist-info/entry_points.txt
flync-1.0.2.dist-info/top_level.txt
flync-1.0.2.dist-info/RECORD
