Metadata-Version: 2.4
Name: flync
Version: 1.0.2
Summary: FLYNC: lncRNA discovery pipeline for Drosophila melanogaster
Author: FLYNC Contributors
License: MIT
Keywords: bioinformatics,lncRNA,genomics,machine-learning,RNA-seq
Classifier: Development Status :: 4 - Beta
Classifier: Intended Audience :: Science/Research
Classifier: Topic :: Scientific/Engineering :: Bio-Informatics
Classifier: Programming Language :: Python :: 3
Classifier: Programming Language :: Python :: 3.11
Requires-Python: >=3.11
License-File: LICENSE
Provides-Extra: features
Requires-Dist: pandas>=2.0.0; extra == "features"
Requires-Dist: numpy>=1.24.0; extra == "features"
Requires-Dist: pyfaidx>=0.7.0; extra == "features"
Requires-Dist: gffutils>=0.12.0; extra == "features"
Requires-Dist: pyranges>=0.0.129; extra == "features"
Requires-Dist: pybigwig>=0.3.22; extra == "features"
Requires-Dist: pybedtools>=0.9.1; extra == "features"
Requires-Dist: biopython>=1.81; extra == "features"
Requires-Dist: tqdm>=4.65.0; extra == "features"
Requires-Dist: requests>=2.31.0; extra == "features"
Provides-Extra: ml
Requires-Dist: scikit-learn>=1.3.0; extra == "ml"
Requires-Dist: joblib>=1.3.0; extra == "ml"
Requires-Dist: optuna>=3.0.0; extra == "ml"
Requires-Dist: mlflow>=2.7.0; extra == "ml"
Requires-Dist: interpret>=0.4.0; extra == "ml"
Provides-Extra: workflow
Requires-Dist: snakemake-minimal>=7.32.0; extra == "workflow"
Provides-Extra: all
Requires-Dist: flync[features,ml,workflow]; extra == "all"
Dynamic: license-file
